[
  {"id":"acc_001","exam":"ACCUPLACER","section":"Reading","question":"Read the passage: 'Although renewable energy sources like wind and solar have grown rapidly, fossil fuels still account for over 80% of global energy consumption.' What is the main idea?","options":[{"label":"A","text":"Fossil fuels remain the dominant energy source despite renewable growth"},{"label":"B","text":"Wind energy is growing faster than solar energy"},{"label":"C","text":"Renewable energy has replaced fossil fuels"},{"label":"D","text":"Global energy consumption is decreasing"}],"correctAnswer":"A","explanation":"The passage contrasts renewable growth with fossil fuel dominance.","skill":"Main Idea","difficulty":"easy"},
  {"id":"acc_002","exam":"ACCUPLACER","section":"Arithmetic","question":"What is 3/4 + 2/3?","options":[{"label":"A","text":"17/12"},{"label":"B","text":"5/7"},{"label":"C","text":"5/12"},{"label":"D","text":"1/2"}],"correctAnswer":"A","explanation":"Common denominator 12: 9/12 + 8/12 = 17/12.","skill":"Fractions","difficulty":"medium"},
  {"id":"acc_003","exam":"ACCUPLACER","section":"Writing","question":"Which sentence is punctuated correctly?","options":[{"label":"A","text":"The professor, who teaches biology, is retiring next year."},{"label":"B","text":"The professor who teaches biology, is retiring next year."},{"label":"C","text":"The professor, who teaches biology is retiring next year."},{"label":"D","text":"The professor who, teaches biology, is retiring next year."}],"correctAnswer":"A","explanation":"Nonrestrictive clause correctly enclosed in commas.","skill":"Punctuation","difficulty":"easy"},
  {"id":"acc_004","exam":"ACCUPLACER","section":"Quantitative Reasoning","question":"If a car travels 240 miles in 4 hours, what is its average speed?","options":[{"label":"A","text":"60 mph"},{"label":"B","text":"45 mph"},{"label":"C","text":"80 mph"},{"label":"D","text":"55 mph"}],"correctAnswer":"A","explanation":"Speed = distance/time = 240/4 = 60 mph.","skill":"Rates","difficulty":"easy"},
  {"id":"acc_005","exam":"ACCUPLACER","section":"Advanced Algebra","question":"Factor completely: x² - 9","options":[{"label":"A","text":"(x + 3)(x - 3)"},{"label":"B","text":"(x - 3)²"},{"label":"C","text":"(x + 9)(x - 1)"},{"label":"D","text":"(x - 9)(x + 1)"}],"correctAnswer":"A","explanation":"Difference of squares: a² - b² = (a+b)(a-b).","skill":"Factoring","difficulty":"medium"},
  {"id":"acc_006","exam":"ACCUPLACER","section":"Reading","question":"The word 'ubiquitous' most nearly means:","options":[{"label":"A","text":"Found everywhere"},{"label":"B","text":"Extremely rare"},{"label":"C","text":"Beautiful"},{"label":"D","text":"Dangerous"}],"correctAnswer":"A","explanation":"'Ubiquitous' means present or found everywhere.","skill":"Vocabulary in Context","difficulty":"medium"},
  {"id":"acc_007","exam":"ACCUPLACER","section":"Arithmetic","question":"Convert 0.375 to a fraction in lowest terms.","options":[{"label":"A","text":"3/8"},{"label":"B","text":"375/100"},{"label":"C","text":"3/4"},{"label":"D","text":"37/100"}],"correctAnswer":"A","explanation":"0.375 = 375/1000 = 3/8.","skill":"Decimals to Fractions","difficulty":"medium"},
  {"id":"acc_008","exam":"ACCUPLACER","section":"Writing","question":"Choose the correct word: 'The new policy will _____ all employees equally.'","options":[{"label":"A","text":"affect"},{"label":"B","text":"effect"},{"label":"C","text":"affection"},{"label":"D","text":"effecting"}],"correctAnswer":"A","explanation":"'Affect' is a verb meaning to influence. 'Effect' is typically a noun.","skill":"Commonly Confused Words","difficulty":"easy"},
  {"id":"acc_009","exam":"ACCUPLACER","section":"Quantitative Reasoning","question":"A pie chart shows 25% for A, 35% for B, and 15% for C. What is D's percentage if there are four categories?","options":[{"label":"A","text":"25%"},{"label":"B","text":"20%"},{"label":"C","text":"30%"},{"label":"D","text":"15%"}],"correctAnswer":"A","explanation":"D = 100% - 25% - 35% - 15% = 25%.","skill":"Data Interpretation","difficulty":"easy"},
  {"id":"acc_010","exam":"ACCUPLACER","section":"Advanced Algebra","question":"Solve: 2x² - 8 = 0","options":[{"label":"A","text":"x = ±2"},{"label":"B","text":"x = ±4"},{"label":"C","text":"x = 2 only"},{"label":"D","text":"x = 4 only"}],"correctAnswer":"A","explanation":"2x² = 8 → x² = 4 → x = ±2.","skill":"Quadratic Equations","difficulty":"medium"},
  {"id":"acc_011","exam":"ACCUPLACER","section":"Reading","question":"Which type of writing attempts to convince the reader?","options":[{"label":"A","text":"Persuasive"},{"label":"B","text":"Narrative"},{"label":"C","text":"Descriptive"},{"label":"D","text":"Expository"}],"correctAnswer":"A","explanation":"Persuasive writing aims to convince the reader to agree with the author's position.","skill":"Text Types","difficulty":"easy"},
  {"id":"acc_012","exam":"ACCUPLACER","section":"Arithmetic","question":"What is 15% of 200?","options":[{"label":"A","text":"30"},{"label":"B","text":"25"},{"label":"C","text":"35"},{"label":"D","text":"20"}],"correctAnswer":"A","explanation":"15% × 200 = 0.15 × 200 = 30.","skill":"Percentages","difficulty":"easy"},
  {"id":"acc_013","exam":"ACCUPLACER","section":"Writing","question":"Which sentence demonstrates correct parallel structure?","options":[{"label":"A","text":"She likes hiking, swimming, and cycling."},{"label":"B","text":"She likes hiking, to swim, and cycling."},{"label":"C","text":"She likes to hike, swimming, and to cycle."},{"label":"D","text":"She likes hiking, she swims, and cycling."}],"correctAnswer":"A","explanation":"All items use gerunds (-ing form) for parallel structure.","skill":"Parallel Structure","difficulty":"medium"},
  {"id":"acc_014","exam":"ACCUPLACER","section":"Quantitative Reasoning","question":"If P(rain) = 0.3, what is P(no rain)?","options":[{"label":"A","text":"0.7"},{"label":"B","text":"0.3"},{"label":"C","text":"0.5"},{"label":"D","text":"1.3"}],"correctAnswer":"A","explanation":"P(not rain) = 1 - 0.3 = 0.7.","skill":"Probability","difficulty":"easy"},
  {"id":"acc_015","exam":"ACCUPLACER","section":"Advanced Algebra","question":"What is the domain of f(x) = 1/(x - 3)?","options":[{"label":"A","text":"All real numbers except x = 3"},{"label":"B","text":"All real numbers"},{"label":"C","text":"x > 3 only"},{"label":"D","text":"x < 3 only"}],"correctAnswer":"A","explanation":"Division by zero is undefined when x = 3.","skill":"Functions","difficulty":"medium"},
  {"id":"acc_016","exam":"ACCUPLACER","section":"Reading","question":"A bibliography is typically found:","options":[{"label":"A","text":"At the end of a research paper"},{"label":"B","text":"At the beginning of an essay"},{"label":"C","text":"In the body paragraphs"},{"label":"D","text":"In the title page"}],"correctAnswer":"A","explanation":"A bibliography lists sources at the end of the document.","skill":"Research Skills","difficulty":"easy"},
  {"id":"acc_017","exam":"ACCUPLACER","section":"Arithmetic","question":"Order from least to greatest: -3, 0.5, -1, 2, -0.5","options":[{"label":"A","text":"-3, -1, -0.5, 0.5, 2"},{"label":"B","text":"-0.5, -1, -3, 0.5, 2"},{"label":"C","text":"2, 0.5, -0.5, -1, -3"},{"label":"D","text":"-3, -0.5, -1, 0.5, 2"}],"correctAnswer":"A","explanation":"On the number line: -3, -1, -0.5, 0.5, 2.","skill":"Number Ordering","difficulty":"easy"},
  {"id":"acc_018","exam":"ACCUPLACER","section":"Writing","question":"Which transition word best shows contrast?","options":[{"label":"A","text":"However"},{"label":"B","text":"Furthermore"},{"label":"C","text":"Similarly"},{"label":"D","text":"Additionally"}],"correctAnswer":"A","explanation":"'However' signals a contrast or opposing idea.","skill":"Transitions","difficulty":"easy"},
  {"id":"acc_019","exam":"ACCUPLACER","section":"Quantitative Reasoning","question":"A garden is 12 ft by 8 ft. What length of fencing is needed?","options":[{"label":"A","text":"40 feet"},{"label":"B","text":"96 feet"},{"label":"C","text":"20 feet"},{"label":"D","text":"48 feet"}],"correctAnswer":"A","explanation":"Perimeter = 2(12 + 8) = 40 feet.","skill":"Perimeter","difficulty":"easy"},
  {"id":"acc_020","exam":"ACCUPLACER","section":"Advanced Algebra","question":"Simplify: (3x²y)(4xy³)","options":[{"label":"A","text":"12x³y⁴"},{"label":"B","text":"7x³y⁴"},{"label":"C","text":"12x²y³"},{"label":"D","text":"7x²y³"}],"correctAnswer":"A","explanation":"3×4=12, x^(2+1)=x³, y^(1+3)=y⁴.","skill":"Exponent Rules","difficulty":"medium"},
  {"id":"acc_021","exam":"ACCUPLACER","section":"Arithmetic","question":"What is -8 + 5?","options":[{"label":"A","text":"-3"},{"label":"B","text":"3"},{"label":"C","text":"-13"},{"label":"D","text":"13"}],"correctAnswer":"A","explanation":"-8 + 5 = -3.","skill":"Integer Operations","difficulty":"easy"},
  {"id":"acc_022","exam":"ACCUPLACER","section":"Reading","question":"An author's purpose for writing an editorial is usually to:","options":[{"label":"A","text":"Persuade readers to agree with an opinion"},{"label":"B","text":"Provide fictional entertainment"},{"label":"C","text":"Report facts objectively"},{"label":"D","text":"Teach a skill"}],"correctAnswer":"A","explanation":"Editorials express opinions and attempt to persuade readers.","skill":"Author's Purpose","difficulty":"easy"},
  {"id":"acc_023","exam":"ACCUPLACER","section":"Writing","question":"Identify the sentence with correct subject-verb agreement:","options":[{"label":"A","text":"The list of items is on the table."},{"label":"B","text":"The list of items are on the table."},{"label":"C","text":"The list of items were on the table."},{"label":"D","text":"The list of items have been on the table."}],"correctAnswer":"A","explanation":"'List' (singular subject) takes 'is,' not 'are.'","skill":"Subject-Verb Agreement","difficulty":"easy"},
  {"id":"acc_024","exam":"ACCUPLACER","section":"Quantitative Reasoning","question":"A shirt originally costs $40 and is marked down 25%. What is the sale price?","options":[{"label":"A","text":"$30"},{"label":"B","text":"$35"},{"label":"C","text":"$25"},{"label":"D","text":"$15"}],"correctAnswer":"A","explanation":"25% of $40 = $10. Sale price = $40 - $10 = $30.","skill":"Percent Applications","difficulty":"easy"},
  {"id":"acc_025","exam":"ACCUPLACER","section":"Advanced Algebra","question":"Solve: 3x + 2 = 5x - 8","options":[{"label":"A","text":"5"},{"label":"B","text":"3"},{"label":"C","text":"-5"},{"label":"D","text":"10"}],"correctAnswer":"A","explanation":"2 + 8 = 5x - 3x → 10 = 2x → x = 5.","skill":"Linear Equations","difficulty":"easy"},
  {"id":"acc_026","exam":"ACCUPLACER","section":"Arithmetic","question":"What is 2/3 of 90?","options":[{"label":"A","text":"60"},{"label":"B","text":"30"},{"label":"C","text":"45"},{"label":"D","text":"72"}],"correctAnswer":"A","explanation":"2/3 × 90 = 180/3 = 60.","skill":"Fractions","difficulty":"easy"},
  {"id":"acc_027","exam":"ACCUPLACER","section":"Reading","question":"Context clues help readers:","options":[{"label":"A","text":"Determine the meaning of unknown words"},{"label":"B","text":"Identify the author"},{"label":"C","text":"Count paragraphs"},{"label":"D","text":"Find the date of publication"}],"correctAnswer":"A","explanation":"Context clues are hints within surrounding text that help define unfamiliar words.","skill":"Vocabulary Strategy","difficulty":"easy"},
  {"id":"acc_028","exam":"ACCUPLACER","section":"Writing","question":"Which is a sentence fragment?","options":[{"label":"A","text":"Running through the park on a sunny day."},{"label":"B","text":"She was running through the park."},{"label":"C","text":"Running through the park, she smiled."},{"label":"D","text":"She ran through the park on a sunny day."}],"correctAnswer":"A","explanation":"A fragment lacks a subject performing a complete action. 'Running through the park' has no main subject or complete verb.","skill":"Sentence Fragments","difficulty":"easy"},
  {"id":"acc_029","exam":"ACCUPLACER","section":"Quantitative Reasoning","question":"If a box contains 4 red, 3 blue, and 3 green balls, what is P(blue)?","options":[{"label":"A","text":"3/10"},{"label":"B","text":"1/3"},{"label":"C","text":"3/7"},{"label":"D","text":"1/10"}],"correctAnswer":"A","explanation":"P(blue) = 3/(4+3+3) = 3/10.","skill":"Probability","difficulty":"easy"},
  {"id":"acc_030","exam":"ACCUPLACER","section":"Advanced Algebra","question":"What is the slope of the line 2y - 6x = 10?","options":[{"label":"A","text":"3"},{"label":"B","text":"-3"},{"label":"C","text":"6"},{"label":"D","text":"5"}],"correctAnswer":"A","explanation":"2y = 6x + 10 → y = 3x + 5. Slope = 3.","skill":"Linear Functions","difficulty":"medium"},
  {"id":"acc_031","exam":"ACCUPLACER","section":"Arithmetic","question":"Round 3.467 to the nearest tenth.","options":[{"label":"A","text":"3.5"},{"label":"B","text":"3.4"},{"label":"C","text":"3.47"},{"label":"D","text":"3.0"}],"correctAnswer":"A","explanation":"The hundredths digit is 6 (≥5), so round up: 3.5.","skill":"Rounding","difficulty":"easy"},
  {"id":"acc_032","exam":"ACCUPLACER","section":"Reading","question":"A summary should include:","options":[{"label":"A","text":"The main ideas in your own words"},{"label":"B","text":"Every detail from the original text"},{"label":"C","text":"Your personal opinions"},{"label":"D","text":"Direct quotes only"}],"correctAnswer":"A","explanation":"A summary condenses the main ideas into your own words without including every detail or personal opinions.","skill":"Summarizing","difficulty":"easy"},
  {"id":"acc_033","exam":"ACCUPLACER","section":"Writing","question":"Choose the correct form: 'Everyone should bring _____ own lunch.'","options":[{"label":"A","text":"their"},{"label":"B","text":"his or her"},{"label":"C","text":"its"},{"label":"D","text":"our"}],"correctAnswer":"A","explanation":"'Their' is now widely accepted as a singular pronoun for indefinite antecedents like 'everyone.'","skill":"Pronoun Agreement","difficulty":"easy"},
  {"id":"acc_034","exam":"ACCUPLACER","section":"Quantitative Reasoning","question":"A student scores 80, 90, 85, and 95 on four tests. What is the mean?","options":[{"label":"A","text":"87.5"},{"label":"B","text":"85"},{"label":"C","text":"90"},{"label":"D","text":"87"}],"correctAnswer":"A","explanation":"(80+90+85+95)/4 = 350/4 = 87.5.","skill":"Statistics","difficulty":"easy"},
  {"id":"acc_035","exam":"ACCUPLACER","section":"Advanced Algebra","question":"Solve: x² + 2x - 15 = 0","options":[{"label":"A","text":"x = 3 or x = -5"},{"label":"B","text":"x = 5 or x = -3"},{"label":"C","text":"x = 15 or x = -1"},{"label":"D","text":"x = -15 or x = 1"}],"correctAnswer":"A","explanation":"Factor: (x+5)(x-3) = 0 → x = -5 or x = 3.","skill":"Quadratic Equations","difficulty":"medium"},
  {"id":"acc_036","exam":"ACCUPLACER","section":"Arithmetic","question":"What is 5/6 - 1/3?","options":[{"label":"A","text":"1/2"},{"label":"B","text":"4/6"},{"label":"C","text":"2/3"},{"label":"D","text":"1/6"}],"correctAnswer":"A","explanation":"Common denominator 6: 5/6 - 2/6 = 3/6 = 1/2.","skill":"Fraction Subtraction","difficulty":"easy"},
  {"id":"acc_037","exam":"ACCUPLACER","section":"Reading","question":"The word 'ambivalent' means:","options":[{"label":"A","text":"Having mixed or conflicting feelings"},{"label":"B","text":"Very certain about something"},{"label":"C","text":"Angry and hostile"},{"label":"D","text":"Uninterested"}],"correctAnswer":"A","explanation":"'Ambivalent' means having contradictory or mixed feelings about something.","skill":"Vocabulary","difficulty":"medium"},
  {"id":"acc_038","exam":"ACCUPLACER","section":"Writing","question":"Which revision corrects the comma splice: 'I went to the store, I bought milk.'","options":[{"label":"A","text":"I went to the store, and I bought milk."},{"label":"B","text":"I went to the store, I, bought milk."},{"label":"C","text":"I went, to the store I bought milk."},{"label":"D","text":"No change needed."}],"correctAnswer":"A","explanation":"Add a coordinating conjunction after the comma to fix the comma splice.","skill":"Comma Splices","difficulty":"easy"},
  {"id":"acc_039","exam":"ACCUPLACER","section":"Quantitative Reasoning","question":"A triangle has a base of 10 and height of 8. What is its area?","options":[{"label":"A","text":"40"},{"label":"B","text":"80"},{"label":"C","text":"18"},{"label":"D","text":"36"}],"correctAnswer":"A","explanation":"Area = ½ × base × height = ½ × 10 × 8 = 40.","skill":"Geometry","difficulty":"easy"},
  {"id":"acc_040","exam":"ACCUPLACER","section":"Advanced Algebra","question":"If f(x) = 2x² - 3x + 1, what is f(0)?","options":[{"label":"A","text":"1"},{"label":"B","text":"0"},{"label":"C","text":"-3"},{"label":"D","text":"2"}],"correctAnswer":"A","explanation":"f(0) = 2(0)² - 3(0) + 1 = 1.","skill":"Function Evaluation","difficulty":"easy"},
  {"id":"acc_041","exam":"ACCUPLACER","section":"Arithmetic","question":"What is (-4) × (-6)?","options":[{"label":"A","text":"24"},{"label":"B","text":"-24"},{"label":"C","text":"10"},{"label":"D","text":"-10"}],"correctAnswer":"A","explanation":"Negative × negative = positive. 4 × 6 = 24.","skill":"Integer Multiplication","difficulty":"easy"},
  {"id":"acc_042","exam":"ACCUPLACER","section":"Reading","question":"An inference requires:","options":[{"label":"A","text":"Using evidence and prior knowledge to draw a conclusion"},{"label":"B","text":"Copying text directly"},{"label":"C","text":"Guessing randomly"},{"label":"D","text":"Only reading the title"}],"correctAnswer":"A","explanation":"Making inferences combines textual evidence with the reader's background knowledge.","skill":"Making Inferences","difficulty":"easy"},
  {"id":"acc_043","exam":"ACCUPLACER","section":"Writing","question":"Which word is a preposition?","options":[{"label":"A","text":"Between"},{"label":"B","text":"Quickly"},{"label":"C","text":"Run"},{"label":"D","text":"Beautiful"}],"correctAnswer":"A","explanation":"'Between' is a preposition showing relationship between nouns.","skill":"Parts of Speech","difficulty":"easy"},
  {"id":"acc_044","exam":"ACCUPLACER","section":"Quantitative Reasoning","question":"Convert 3 feet to inches.","options":[{"label":"A","text":"36 inches"},{"label":"B","text":"12 inches"},{"label":"C","text":"24 inches"},{"label":"D","text":"48 inches"}],"correctAnswer":"A","explanation":"1 foot = 12 inches. 3 × 12 = 36 inches.","skill":"Unit Conversion","difficulty":"easy"},
  {"id":"acc_045","exam":"ACCUPLACER","section":"Advanced Algebra","question":"Simplify: √72","options":[{"label":"A","text":"6√2"},{"label":"B","text":"36"},{"label":"C","text":"8√3"},{"label":"D","text":"12"}],"correctAnswer":"A","explanation":"√72 = √(36×2) = 6√2.","skill":"Radicals","difficulty":"medium"},
  {"id":"acc_046","exam":"ACCUPLACER","section":"Arithmetic","question":"What is 1.5 × 2.4?","options":[{"label":"A","text":"3.6"},{"label":"B","text":"3.9"},{"label":"C","text":"3.54"},{"label":"D","text":"3.06"}],"correctAnswer":"A","explanation":"1.5 × 2.4 = 3.6.","skill":"Decimal Multiplication","difficulty":"easy"},
  {"id":"acc_047","exam":"ACCUPLACER","section":"Reading","question":"Which best describes the purpose of a topic sentence?","options":[{"label":"A","text":"It introduces the main idea of a paragraph"},{"label":"B","text":"It ends the essay"},{"label":"C","text":"It provides a citation"},{"label":"D","text":"It is always a question"}],"correctAnswer":"A","explanation":"A topic sentence introduces the paragraph's main idea and guides what follows.","skill":"Paragraph Structure","difficulty":"easy"},
  {"id":"acc_048","exam":"ACCUPLACER","section":"Writing","question":"Which sentence is in active voice?","options":[{"label":"A","text":"The teacher graded the exams."},{"label":"B","text":"The exams were graded by the teacher."},{"label":"C","text":"The exams were graded."},{"label":"D","text":"Grading was done by the teacher."}],"correctAnswer":"A","explanation":"In active voice, the subject (teacher) performs the action (graded).","skill":"Active vs Passive Voice","difficulty":"easy"},
  {"id":"acc_049","exam":"ACCUPLACER","section":"Quantitative Reasoning","question":"A recipe serves 6. To serve 9, multiply all ingredients by:","options":[{"label":"A","text":"1.5"},{"label":"B","text":"3"},{"label":"C","text":"2"},{"label":"D","text":"0.67"}],"correctAnswer":"A","explanation":"Scale factor = 9/6 = 1.5.","skill":"Proportions","difficulty":"easy"},
  {"id":"acc_050","exam":"ACCUPLACER","section":"Advanced Algebra","question":"What is the y-intercept of y = -3x + 7?","options":[{"label":"A","text":"7"},{"label":"B","text":"-3"},{"label":"C","text":"0"},{"label":"D","text":"3"}],"correctAnswer":"A","explanation":"In y = mx + b, the y-intercept b = 7.","skill":"Linear Functions","difficulty":"easy"},
  {"id":"acc_051","exam":"ACCUPLACER","section":"Arithmetic","question":"Reduce 18/24 to lowest terms.","options":[{"label":"A","text":"3/4"},{"label":"B","text":"9/12"},{"label":"C","text":"6/8"},{"label":"D","text":"2/3"}],"correctAnswer":"A","explanation":"GCF of 18 and 24 is 6. 18÷6=3, 24÷6=4.","skill":"Simplifying Fractions","difficulty":"easy"},
  {"id":"acc_052","exam":"ACCUPLACER","section":"Reading","question":"Which organizational pattern presents events in time order?","options":[{"label":"A","text":"Chronological"},{"label":"B","text":"Compare and contrast"},{"label":"C","text":"Cause and effect"},{"label":"D","text":"Classification"}],"correctAnswer":"A","explanation":"Chronological order arranges events sequentially by time.","skill":"Text Structure","difficulty":"easy"},
  {"id":"acc_053","exam":"ACCUPLACER","section":"Writing","question":"Fix the dangling modifier: 'After reading the report, concerns were raised.'","options":[{"label":"A","text":"After reading the report, the committee raised concerns."},{"label":"B","text":"After reading the report, concerns were raised by them."},{"label":"C","text":"The report after reading raised concerns."},{"label":"D","text":"No change needed."}],"correctAnswer":"A","explanation":"Specify WHO read the report (the committee) to fix the dangling modifier.","skill":"Modifiers","difficulty":"medium"},
  {"id":"acc_054","exam":"ACCUPLACER","section":"Quantitative Reasoning","question":"What is the volume of a box 5 cm × 4 cm × 3 cm?","options":[{"label":"A","text":"60 cm³"},{"label":"B","text":"12 cm³"},{"label":"C","text":"47 cm³"},{"label":"D","text":"24 cm³"}],"correctAnswer":"A","explanation":"Volume = 5 × 4 × 3 = 60 cm³.","skill":"Volume","difficulty":"easy"},
  {"id":"acc_055","exam":"ACCUPLACER","section":"Advanced Algebra","question":"Solve: |x - 5| = 3","options":[{"label":"A","text":"x = 8 or x = 2"},{"label":"B","text":"x = 8 only"},{"label":"C","text":"x = 2 only"},{"label":"D","text":"x = -8 or x = -2"}],"correctAnswer":"A","explanation":"x - 5 = 3 → x = 8, or x - 5 = -3 → x = 2.","skill":"Absolute Value","difficulty":"medium"},
  {"id":"acc_056","exam":"ACCUPLACER","section":"Arithmetic","question":"What is 20% expressed as a decimal?","options":[{"label":"A","text":"0.2"},{"label":"B","text":"0.02"},{"label":"C","text":"2.0"},{"label":"D","text":"20.0"}],"correctAnswer":"A","explanation":"20% = 20/100 = 0.2.","skill":"Percent to Decimal","difficulty":"easy"},
  {"id":"acc_057","exam":"ACCUPLACER","section":"Reading","question":"A credible source is one that:","options":[{"label":"A","text":"Is reliable, accurate, and written by an expert"},{"label":"B","text":"Is the most recent"},{"label":"C","text":"Has the most pages"},{"label":"D","text":"Is the cheapest to access"}],"correctAnswer":"A","explanation":"Credible sources are reliable, well-researched, and written by qualified authors.","skill":"Source Evaluation","difficulty":"easy"},
  {"id":"acc_058","exam":"ACCUPLACER","section":"Writing","question":"Which is correct: 'lay' or 'lie'? 'I need to _____ down.'","options":[{"label":"A","text":"lie"},{"label":"B","text":"lay"},{"label":"C","text":"laid"},{"label":"D","text":"lain"}],"correctAnswer":"A","explanation":"'Lie' means to recline (intransitive). 'Lay' means to put something down (transitive, needs an object).","skill":"Commonly Confused Verbs","difficulty":"medium"},
  {"id":"acc_059","exam":"ACCUPLACER","section":"Quantitative Reasoning","question":"A class has 12 boys and 18 girls. What is the ratio of boys to girls in simplest form?","options":[{"label":"A","text":"2:3"},{"label":"B","text":"12:18"},{"label":"C","text":"3:2"},{"label":"D","text":"1:2"}],"correctAnswer":"A","explanation":"12:18 simplified by dividing by 6 = 2:3.","skill":"Ratios","difficulty":"easy"},
  {"id":"acc_060","exam":"ACCUPLACER","section":"Advanced Algebra","question":"What is the range of f(x) = x² for all real x?","options":[{"label":"A","text":"y ≥ 0"},{"label":"B","text":"All real numbers"},{"label":"C","text":"y > 0"},{"label":"D","text":"y ≤ 0"}],"correctAnswer":"A","explanation":"x² is always non-negative, so the range is y ≥ 0.","skill":"Functions","difficulty":"medium"},
  {"id":"acc_061","exam":"ACCUPLACER","section":"Arithmetic","question":"What is 7 × 8?","options":[{"label":"A","text":"56"},{"label":"B","text":"54"},{"label":"C","text":"63"},{"label":"D","text":"48"}],"correctAnswer":"A","explanation":"7 × 8 = 56.","skill":"Multiplication Facts","difficulty":"easy"},
  {"id":"acc_062","exam":"ACCUPLACER","section":"Reading","question":"A conclusion paragraph should NOT:","options":[{"label":"A","text":"Introduce entirely new arguments"},{"label":"B","text":"Summarize main points"},{"label":"C","text":"Restate the thesis"},{"label":"D","text":"Provide a final thought"}],"correctAnswer":"A","explanation":"Conclusions should synthesize, not introduce new ideas. New arguments belong in body paragraphs.","skill":"Essay Structure","difficulty":"easy"},
  {"id":"acc_063","exam":"ACCUPLACER","section":"Writing","question":"Which is correct? 'The company announced _____ new policy.'","options":[{"label":"A","text":"its"},{"label":"B","text":"it's"},{"label":"C","text":"its'"},{"label":"D","text":"their's"}],"correctAnswer":"A","explanation":"'Its' (no apostrophe) is possessive. 'It's' means 'it is.'","skill":"Possessives","difficulty":"easy"},
  {"id":"acc_064","exam":"ACCUPLACER","section":"Quantitative Reasoning","question":"If sales tax is 7%, what is the total cost of a $50 purchase?","options":[{"label":"A","text":"$53.50"},{"label":"B","text":"$57.00"},{"label":"C","text":"$50.70"},{"label":"D","text":"$56.50"}],"correctAnswer":"A","explanation":"Tax = 7% × $50 = $3.50. Total = $53.50.","skill":"Tax Calculations","difficulty":"easy"},
  {"id":"acc_065","exam":"ACCUPLACER","section":"Advanced Algebra","question":"Factor: x² - 5x + 6","options":[{"label":"A","text":"(x - 2)(x - 3)"},{"label":"B","text":"(x + 2)(x + 3)"},{"label":"C","text":"(x - 1)(x - 6)"},{"label":"D","text":"(x + 1)(x - 6)"}],"correctAnswer":"A","explanation":"Find two numbers that multiply to 6 and add to -5: -2 and -3.","skill":"Factoring Trinomials","difficulty":"medium"},
  {"id":"acc_066","exam":"ACCUPLACER","section":"Arithmetic","question":"Express 7/20 as a percent.","options":[{"label":"A","text":"35%"},{"label":"B","text":"70%"},{"label":"C","text":"7%"},{"label":"D","text":"14%"}],"correctAnswer":"A","explanation":"7/20 = 35/100 = 35%.","skill":"Fraction to Percent","difficulty":"easy"},
  {"id":"acc_067","exam":"ACCUPLACER","section":"Reading","question":"Tone in writing is best described as:","options":[{"label":"A","text":"The author's attitude toward the subject"},{"label":"B","text":"The volume of the writing"},{"label":"C","text":"The number of paragraphs"},{"label":"D","text":"The font style used"}],"correctAnswer":"A","explanation":"Tone reflects the author's attitude — formal, sarcastic, optimistic, critical, etc.","skill":"Tone Analysis","difficulty":"easy"},
  {"id":"acc_068","exam":"ACCUPLACER","section":"Writing","question":"Which revision eliminates wordiness? 'Due to the fact that it was raining, we stayed inside.'","options":[{"label":"A","text":"Because it was raining, we stayed inside."},{"label":"B","text":"Due to the rain factor, we stayed inside."},{"label":"C","text":"It being the case that rain occurred, we stayed inside."},{"label":"D","text":"No change needed."}],"correctAnswer":"A","explanation":"Replace 'due to the fact that' with the concise 'because.'","skill":"Conciseness","difficulty":"easy"},
  {"id":"acc_069","exam":"ACCUPLACER","section":"Quantitative Reasoning","question":"A rectangle has length 2x and width x. If the perimeter is 36, find x.","options":[{"label":"A","text":"6"},{"label":"B","text":"9"},{"label":"C","text":"12"},{"label":"D","text":"3"}],"correctAnswer":"A","explanation":"P = 2(2x + x) = 6x = 36 → x = 6.","skill":"Algebraic Geometry","difficulty":"medium"},
  {"id":"acc_070","exam":"ACCUPLACER","section":"Advanced Algebra","question":"Solve: 2^x = 32","options":[{"label":"A","text":"5"},{"label":"B","text":"4"},{"label":"C","text":"6"},{"label":"D","text":"16"}],"correctAnswer":"A","explanation":"32 = 2⁵, so x = 5.","skill":"Exponential Equations","difficulty":"medium"},
  {"id":"acc_071","exam":"ACCUPLACER","section":"Arithmetic","question":"Divide: 144 ÷ 12","options":[{"label":"A","text":"12"},{"label":"B","text":"11"},{"label":"C","text":"14"},{"label":"D","text":"132"}],"correctAnswer":"A","explanation":"144 ÷ 12 = 12.","skill":"Division","difficulty":"easy"},
  {"id":"acc_072","exam":"ACCUPLACER","section":"Reading","question":"Which is NOT a reliable source for a research paper?","options":[{"label":"A","text":"An anonymous blog post"},{"label":"B","text":"A peer-reviewed journal"},{"label":"C","text":"A government website"},{"label":"D","text":"A university publication"}],"correctAnswer":"A","explanation":"Anonymous blogs lack accountability and credibility compared to vetted, peer-reviewed sources.","skill":"Source Evaluation","difficulty":"easy"},
  {"id":"acc_073","exam":"ACCUPLACER","section":"Writing","question":"Which sentence uses a semicolon correctly?","options":[{"label":"A","text":"I love hiking; my brother prefers cycling."},{"label":"B","text":"I love hiking; and my brother prefers cycling."},{"label":"C","text":"I love; hiking my brother prefers cycling."},{"label":"D","text":"I love hiking, my brother; prefers cycling."}],"correctAnswer":"A","explanation":"A semicolon joins two related independent clauses without a conjunction.","skill":"Semicolon Usage","difficulty":"medium"},
  {"id":"acc_074","exam":"ACCUPLACER","section":"Quantitative Reasoning","question":"What is the mean of 5, 10, 15, 20, 25?","options":[{"label":"A","text":"15"},{"label":"B","text":"10"},{"label":"C","text":"20"},{"label":"D","text":"12.5"}],"correctAnswer":"A","explanation":"(5+10+15+20+25)/5 = 75/5 = 15.","skill":"Mean","difficulty":"easy"},
  {"id":"acc_075","exam":"ACCUPLACER","section":"Advanced Algebra","question":"What is the vertex of y = (x - 3)² + 2?","options":[{"label":"A","text":"(3, 2)"},{"label":"B","text":"(-3, 2)"},{"label":"C","text":"(3, -2)"},{"label":"D","text":"(2, 3)"}],"correctAnswer":"A","explanation":"Vertex form y = (x-h)² + k gives vertex (h,k) = (3,2).","skill":"Quadratic Functions","difficulty":"medium"},
  {"id":"acc_076","exam":"ACCUPLACER","section":"Arithmetic","question":"What is 3.2 - 1.78?","options":[{"label":"A","text":"1.42"},{"label":"B","text":"1.52"},{"label":"C","text":"2.42"},{"label":"D","text":"1.32"}],"correctAnswer":"A","explanation":"3.20 - 1.78 = 1.42.","skill":"Decimal Subtraction","difficulty":"easy"},
  {"id":"acc_077","exam":"ACCUPLACER","section":"Reading","question":"A fact is different from an opinion because a fact:","options":[{"label":"A","text":"Can be verified as true or false"},{"label":"B","text":"Is always interesting"},{"label":"C","text":"Cannot be proven"},{"label":"D","text":"Is someone's personal belief"}],"correctAnswer":"A","explanation":"Facts are objective and verifiable. Opinions are subjective beliefs that cannot be proven true or false.","skill":"Fact vs Opinion","difficulty":"easy"},
  {"id":"acc_078","exam":"ACCUPLACER","section":"Writing","question":"Which sentence correctly uses 'who'?","options":[{"label":"A","text":"The student who studied hard passed the exam."},{"label":"B","text":"The student whom studied hard passed the exam."},{"label":"C","text":"The student which studied hard passed the exam."},{"label":"D","text":"The student what studied hard passed the exam."}],"correctAnswer":"A","explanation":"'Who' is used for people as a subject pronoun.","skill":"Relative Pronouns","difficulty":"easy"},
  {"id":"acc_079","exam":"ACCUPLACER","section":"Quantitative Reasoning","question":"A circular pool has radius 10 ft. What is its area? (π ≈ 3.14)","options":[{"label":"A","text":"314 sq ft"},{"label":"B","text":"62.8 sq ft"},{"label":"C","text":"31.4 sq ft"},{"label":"D","text":"100 sq ft"}],"correctAnswer":"A","explanation":"Area = πr² = 3.14 × 100 = 314 sq ft.","skill":"Circle Area","difficulty":"medium"},
  {"id":"acc_080","exam":"ACCUPLACER","section":"Advanced Algebra","question":"Simplify: (x + 3)² ","options":[{"label":"A","text":"x² + 6x + 9"},{"label":"B","text":"x² + 9"},{"label":"C","text":"x² + 3x + 9"},{"label":"D","text":"2x + 6"}],"correctAnswer":"A","explanation":"(x+3)² = x² + 2(3)(x) + 9 = x² + 6x + 9.","skill":"Expanding Binomials","difficulty":"medium"},
  {"id":"acc_081","exam":"ACCUPLACER","section":"Arithmetic","question":"What is 5/8 as a decimal?","options":[{"label":"A","text":"0.625"},{"label":"B","text":"0.58"},{"label":"C","text":"0.85"},{"label":"D","text":"0.125"}],"correctAnswer":"A","explanation":"5 ÷ 8 = 0.625.","skill":"Fraction to Decimal","difficulty":"easy"},
  {"id":"acc_082","exam":"ACCUPLACER","section":"Reading","question":"Which word signal indicates a contrast?","options":[{"label":"A","text":"Although"},{"label":"B","text":"Because"},{"label":"C","text":"Since"},{"label":"D","text":"Moreover"}],"correctAnswer":"A","explanation":"'Although' signals a contrast or concession between ideas.","skill":"Signal Words","difficulty":"easy"},
  {"id":"acc_083","exam":"ACCUPLACER","section":"Writing","question":"Which is a compound-complex sentence?","options":[{"label":"A","text":"Although it rained, we went out, and we had a great time."},{"label":"B","text":"We went out."},{"label":"C","text":"We went out and had a great time."},{"label":"D","text":"Although it rained, we went out."}],"correctAnswer":"A","explanation":"Compound-complex has at least two independent clauses and one dependent clause.","skill":"Sentence Types","difficulty":"medium"},
  {"id":"acc_084","exam":"ACCUPLACER","section":"Quantitative Reasoning","question":"If a worker earns $15/hour and works 37.5 hours, what is the gross pay?","options":[{"label":"A","text":"$562.50"},{"label":"B","text":"$550"},{"label":"C","text":"$525"},{"label":"D","text":"$575"}],"correctAnswer":"A","explanation":"$15 × 37.5 = $562.50.","skill":"Wages","difficulty":"easy"},
  {"id":"acc_085","exam":"ACCUPLACER","section":"Advanced Algebra","question":"What are the solutions of x² - 4x = 0?","options":[{"label":"A","text":"x = 0 or x = 4"},{"label":"B","text":"x = 4 only"},{"label":"C","text":"x = 0 only"},{"label":"D","text":"x = -4 or x = 0"}],"correctAnswer":"A","explanation":"x(x-4) = 0 → x = 0 or x = 4.","skill":"Factoring","difficulty":"medium"},
  {"id":"acc_086","exam":"ACCUPLACER","section":"Arithmetic","question":"What is 6² + 4²?","options":[{"label":"A","text":"52"},{"label":"B","text":"100"},{"label":"C","text":"20"},{"label":"D","text":"10"}],"correctAnswer":"A","explanation":"36 + 16 = 52.","skill":"Exponents","difficulty":"easy"},
  {"id":"acc_087","exam":"ACCUPLACER","section":"Reading","question":"Supporting details in a paragraph serve to:","options":[{"label":"A","text":"Explain, prove, or develop the main idea"},{"label":"B","text":"Introduce a new topic"},{"label":"C","text":"Contradict the thesis"},{"label":"D","text":"Provide the title"}],"correctAnswer":"A","explanation":"Supporting details provide evidence, examples, and explanations that develop the main idea.","skill":"Paragraph Structure","difficulty":"easy"},
  {"id":"acc_088","exam":"ACCUPLACER","section":"Writing","question":"Choose the correct homophone: 'The _____ reason for failure was poor planning.'","options":[{"label":"A","text":"principal"},{"label":"B","text":"principle"},{"label":"C","text":"principel"},{"label":"D","text":"prinsipal"}],"correctAnswer":"A","explanation":"'Principal' means main or chief. 'Principle' means a rule or standard.","skill":"Homophones","difficulty":"medium"},
  {"id":"acc_089","exam":"ACCUPLACER","section":"Quantitative Reasoning","question":"A car's odometer reads 45,230 on Monday and 45,680 on Friday. How many miles were driven?","options":[{"label":"A","text":"450"},{"label":"B","text":"550"},{"label":"C","text":"350"},{"label":"D","text":"500"}],"correctAnswer":"A","explanation":"45,680 - 45,230 = 450 miles.","skill":"Subtraction","difficulty":"easy"},
  {"id":"acc_090","exam":"ACCUPLACER","section":"Advanced Algebra","question":"What is log₂(8)?","options":[{"label":"A","text":"3"},{"label":"B","text":"4"},{"label":"C","text":"2"},{"label":"D","text":"8"}],"correctAnswer":"A","explanation":"2³ = 8, so log₂(8) = 3.","skill":"Logarithms","difficulty":"medium"},
  {"id":"acc_091","exam":"ACCUPLACER","section":"Arithmetic","question":"Convert 1/4 to a percentage.","options":[{"label":"A","text":"25%"},{"label":"B","text":"40%"},{"label":"C","text":"4%"},{"label":"D","text":"50%"}],"correctAnswer":"A","explanation":"1/4 = 0.25 = 25%.","skill":"Percent Conversion","difficulty":"easy"},
  {"id":"acc_092","exam":"ACCUPLACER","section":"Reading","question":"Bias can be detected in writing through:","options":[{"label":"A","text":"Loaded language and one-sided arguments"},{"label":"B","text":"Use of statistics"},{"label":"C","text":"Paragraph length"},{"label":"D","text":"Publication date"}],"correctAnswer":"A","explanation":"Loaded or emotional language and presenting only one perspective are indicators of bias.","skill":"Critical Reading","difficulty":"medium"},
  {"id":"acc_093","exam":"ACCUPLACER","section":"Writing","question":"Which is the best thesis statement?","options":[{"label":"A","text":"Public schools should require financial literacy courses to prepare students for real-world challenges."},{"label":"B","text":"Schools are interesting."},{"label":"C","text":"This essay is about schools."},{"label":"D","text":"Money is important."}],"correctAnswer":"A","explanation":"A strong thesis is specific, arguable, and states a clear position.","skill":"Thesis Statements","difficulty":"easy"},
  {"id":"acc_094","exam":"ACCUPLACER","section":"Quantitative Reasoning","question":"A ladder reaches 12 feet up a wall. The base is 5 feet from the wall. How long is the ladder?","options":[{"label":"A","text":"13 feet"},{"label":"B","text":"17 feet"},{"label":"C","text":"7 feet"},{"label":"D","text":"15 feet"}],"correctAnswer":"A","explanation":"c² = 12² + 5² = 144 + 25 = 169 → c = 13.","skill":"Pythagorean Theorem","difficulty":"medium"},
  {"id":"acc_095","exam":"ACCUPLACER","section":"Advanced Algebra","question":"Solve: 3/(x-1) = 6","options":[{"label":"A","text":"x = 3/2"},{"label":"B","text":"x = 2"},{"label":"C","text":"x = 1/2"},{"label":"D","text":"x = 3"}],"correctAnswer":"A","explanation":"3 = 6(x-1) → 3 = 6x - 6 → 9 = 6x → x = 3/2.","skill":"Rational Equations","difficulty":"medium"},
  {"id":"acc_096","exam":"ACCUPLACER","section":"Arithmetic","question":"What is the reciprocal of 5/7?","options":[{"label":"A","text":"7/5"},{"label":"B","text":"5/7"},{"label":"C","text":"1/5"},{"label":"D","text":"1/7"}],"correctAnswer":"A","explanation":"The reciprocal flips numerator and denominator: 5/7 → 7/5.","skill":"Reciprocals","difficulty":"easy"},
  {"id":"acc_097","exam":"ACCUPLACER","section":"Reading","question":"A text that explains how something works uses which structure?","options":[{"label":"A","text":"Process/Sequential"},{"label":"B","text":"Persuasive"},{"label":"C","text":"Narrative"},{"label":"D","text":"Descriptive"}],"correctAnswer":"A","explanation":"Process or sequential structure explains how something works or how to do something, step by step.","skill":"Text Structure","difficulty":"easy"},
  {"id":"acc_098","exam":"ACCUPLACER","section":"Writing","question":"Fix the agreement error: 'The team are winning.'","options":[{"label":"A","text":"The team is winning."},{"label":"B","text":"The team were winning."},{"label":"C","text":"The teams is winning."},{"label":"D","text":"No change needed."}],"correctAnswer":"A","explanation":"'Team' is a singular collective noun in American English, requiring 'is.'","skill":"Subject-Verb Agreement","difficulty":"easy"},
  {"id":"acc_099","exam":"ACCUPLACER","section":"Quantitative Reasoning","question":"A bag has 5 red and 5 blue marbles. You draw 2 without replacement. What is P(both red)?","options":[{"label":"A","text":"2/9"},{"label":"B","text":"1/4"},{"label":"C","text":"5/10"},{"label":"D","text":"1/2"}],"correctAnswer":"A","explanation":"P = (5/10)(4/9) = 20/90 = 2/9.","skill":"Probability Without Replacement","difficulty":"medium"},
  {"id":"acc_100","exam":"ACCUPLACER","section":"Advanced Algebra","question":"Solve the system: y = 2x + 1 and y = -x + 7","options":[{"label":"A","text":"x = 2, y = 5"},{"label":"B","text":"x = 3, y = 4"},{"label":"C","text":"x = 1, y = 3"},{"label":"D","text":"x = 4, y = 3"}],"correctAnswer":"A","explanation":"2x + 1 = -x + 7 → 3x = 6 → x = 2, y = 5.","skill":"Systems of Equations","difficulty":"medium"},
  {"id":"acc_101","exam":"ACCUPLACER","section":"Arithmetic","question":"What is 4/5 × 3/7?","options":[{"label":"A","text":"12/35"},{"label":"B","text":"7/12"},{"label":"C","text":"12/7"},{"label":"D","text":"4/7"}],"correctAnswer":"A","explanation":"Multiply numerators and denominators: 4×3=12, 5×7=35.","skill":"Fraction Multiplication","difficulty":"easy"},
  {"id":"acc_102","exam":"ACCUPLACER","section":"Reading","question":"An allegory is:","options":[{"label":"A","text":"A story with characters and events that symbolize deeper meanings"},{"label":"B","text":"A comparison using 'like'"},{"label":"C","text":"An extreme exaggeration"},{"label":"D","text":"A repeated sound pattern"}],"correctAnswer":"A","explanation":"An allegory uses symbolic characters and events to represent abstract ideas or moral lessons.","skill":"Literary Terms","difficulty":"medium"},
  {"id":"acc_103","exam":"ACCUPLACER","section":"Writing","question":"Which sentence avoids a split infinitive?","options":[{"label":"A","text":"She wanted to learn quickly."},{"label":"B","text":"She wanted to quickly learn."},{"label":"C","text":"She wanted quickly to learn."},{"label":"D","text":"Quickly she wanted to learn."}],"correctAnswer":"A","explanation":"A split infinitive places a word between 'to' and the verb. 'To learn quickly' avoids splitting.","skill":"Grammar","difficulty":"medium"},
  {"id":"acc_104","exam":"ACCUPLACER","section":"Quantitative Reasoning","question":"A cylindrical tank has radius 5 and height 10. What is its volume? (π ≈ 3.14)","options":[{"label":"A","text":"785"},{"label":"B","text":"157"},{"label":"C","text":"314"},{"label":"D","text":"1570"}],"correctAnswer":"A","explanation":"V = πr²h = 3.14 × 25 × 10 = 785.","skill":"Cylinder Volume","difficulty":"medium"},
  {"id":"acc_105","exam":"ACCUPLACER","section":"Advanced Algebra","question":"What is the discriminant of x² - 6x + 9 = 0?","options":[{"label":"A","text":"0"},{"label":"B","text":"36"},{"label":"C","text":"-36"},{"label":"D","text":"72"}],"correctAnswer":"A","explanation":"D = b²-4ac = 36-36 = 0. This means one repeated real root.","skill":"Discriminant","difficulty":"medium"},
  {"id":"acc_106","exam":"ACCUPLACER","section":"Arithmetic","question":"What is 100 ÷ 0.25?","options":[{"label":"A","text":"400"},{"label":"B","text":"25"},{"label":"C","text":"4"},{"label":"D","text":"250"}],"correctAnswer":"A","explanation":"Dividing by 0.25 is the same as multiplying by 4. 100 × 4 = 400.","skill":"Decimal Division","difficulty":"medium"},
  {"id":"acc_107","exam":"ACCUPLACER","section":"Reading","question":"The phrase 'a wolf in sheep's clothing' is an example of:","options":[{"label":"A","text":"An idiom"},{"label":"B","text":"A simile"},{"label":"C","text":"Onomatopoeia"},{"label":"D","text":"Alliteration"}],"correctAnswer":"A","explanation":"An idiom is a phrase with a figurative meaning different from its literal meaning.","skill":"Figurative Language","difficulty":"easy"},
  {"id":"acc_108","exam":"ACCUPLACER","section":"Writing","question":"Which is the correct comparative form?","options":[{"label":"A","text":"She is more intelligent than her brother."},{"label":"B","text":"She is more intelligenter than her brother."},{"label":"C","text":"She is intelligenter than her brother."},{"label":"D","text":"She is most intelligent than her brother."}],"correctAnswer":"A","explanation":"Multi-syllable adjectives use 'more' for comparison, not '-er.'","skill":"Comparative Forms","difficulty":"easy"},
  {"id":"acc_109","exam":"ACCUPLACER","section":"Quantitative Reasoning","question":"A store sells pens at 3 for $2. How much would 12 pens cost?","options":[{"label":"A","text":"$8"},{"label":"B","text":"$6"},{"label":"C","text":"$12"},{"label":"D","text":"$24"}],"correctAnswer":"A","explanation":"12 ÷ 3 = 4 groups. 4 × $2 = $8.","skill":"Unit Pricing","difficulty":"easy"},
  {"id":"acc_110","exam":"ACCUPLACER","section":"Advanced Algebra","question":"Simplify: (2x-1)(3x+4)","options":[{"label":"A","text":"6x² + 5x - 4"},{"label":"B","text":"6x² - 4"},{"label":"C","text":"6x² + 8x - 3x - 4"},{"label":"D","text":"5x + 3"}],"correctAnswer":"A","explanation":"FOIL: 6x² + 8x - 3x - 4 = 6x² + 5x - 4.","skill":"Polynomial Multiplication","difficulty":"medium"},
  {"id":"acc_111","exam":"ACCUPLACER","section":"Arithmetic","question":"Estimate: 398 × 21","options":[{"label":"A","text":"About 8,000"},{"label":"B","text":"About 4,000"},{"label":"C","text":"About 12,000"},{"label":"D","text":"About 6,000"}],"correctAnswer":"A","explanation":"400 × 20 = 8,000. Actual: 8,358.","skill":"Estimation","difficulty":"easy"},
  {"id":"acc_112","exam":"ACCUPLACER","section":"Reading","question":"A bibliography differs from a works cited page because a bibliography:","options":[{"label":"A","text":"May include sources that were consulted but not directly cited"},{"label":"B","text":"Only includes books"},{"label":"C","text":"Is shorter"},{"label":"D","text":"Doesn't need alphabetical order"}],"correctAnswer":"A","explanation":"A bibliography can include all sources consulted, while works cited lists only directly referenced sources.","skill":"Research Writing","difficulty":"medium"},
  {"id":"acc_113","exam":"ACCUPLACER","section":"Writing","question":"Which revision improves clarity? 'The thing about the situation is that it's complicated.'","options":[{"label":"A","text":"The situation is complicated."},{"label":"B","text":"The thing is complicated about the situation."},{"label":"C","text":"It's a complicated thing, the situation."},{"label":"D","text":"No change needed."}],"correctAnswer":"A","explanation":"Remove filler words ('the thing about') for clarity and directness.","skill":"Conciseness","difficulty":"easy"},
  {"id":"acc_114","exam":"ACCUPLACER","section":"Quantitative Reasoning","question":"How many feet are in 2 miles?","options":[{"label":"A","text":"10,560"},{"label":"B","text":"5,280"},{"label":"C","text":"2,640"},{"label":"D","text":"15,840"}],"correctAnswer":"A","explanation":"1 mile = 5,280 feet. 2 × 5,280 = 10,560 feet.","skill":"Unit Conversion","difficulty":"easy"},
  {"id":"acc_115","exam":"ACCUPLACER","section":"Advanced Algebra","question":"If g(x) = √(x + 4), what is the domain?","options":[{"label":"A","text":"x ≥ -4"},{"label":"B","text":"x ≥ 0"},{"label":"C","text":"All real numbers"},{"label":"D","text":"x > -4"}],"correctAnswer":"A","explanation":"The expression under the square root must be ≥ 0: x + 4 ≥ 0 → x ≥ -4.","skill":"Domain","difficulty":"medium"},
  {"id":"acc_116","exam":"ACCUPLACER","section":"Arithmetic","question":"What is 3/4 expressed as a decimal?","options":[{"label":"A","text":"0.75"},{"label":"B","text":"0.34"},{"label":"C","text":"0.43"},{"label":"D","text":"1.33"}],"correctAnswer":"A","explanation":"3 ÷ 4 = 0.75.","skill":"Fraction to Decimal","difficulty":"easy"},
  {"id":"acc_117","exam":"ACCUPLACER","section":"Reading","question":"Connotation refers to:","options":[{"label":"A","text":"The emotional or cultural association of a word"},{"label":"B","text":"The dictionary definition"},{"label":"C","text":"The pronunciation of a word"},{"label":"D","text":"The spelling of a word"}],"correctAnswer":"A","explanation":"Connotation is the implied meaning beyond the literal definition (denotation).","skill":"Vocabulary","difficulty":"medium"},
  {"id":"acc_118","exam":"ACCUPLACER","section":"Writing","question":"Which is correct: 'less' or 'fewer'? 'There are _____ students today.'","options":[{"label":"A","text":"fewer"},{"label":"B","text":"less"},{"label":"C","text":"lesser"},{"label":"D","text":"fewest"}],"correctAnswer":"A","explanation":"'Fewer' is for countable nouns (students). 'Less' is for uncountable nouns.","skill":"Word Choice","difficulty":"easy"},
  {"id":"acc_119","exam":"ACCUPLACER","section":"Quantitative Reasoning","question":"A right triangle has legs 8 and 15. What is the hypotenuse?","options":[{"label":"A","text":"17"},{"label":"B","text":"23"},{"label":"C","text":"12"},{"label":"D","text":"20"}],"correctAnswer":"A","explanation":"c² = 64 + 225 = 289 → c = 17.","skill":"Pythagorean Theorem","difficulty":"medium"},
  {"id":"acc_120","exam":"ACCUPLACER","section":"Advanced Algebra","question":"What is the inverse of f(x) = 2x + 6?","options":[{"label":"A","text":"f⁻¹(x) = (x - 6)/2"},{"label":"B","text":"f⁻¹(x) = 2x - 6"},{"label":"C","text":"f⁻¹(x) = x/2 + 6"},{"label":"D","text":"f⁻¹(x) = -2x - 6"}],"correctAnswer":"A","explanation":"Swap x and y: x = 2y + 6 → x - 6 = 2y → y = (x-6)/2.","skill":"Inverse Functions","difficulty":"medium"},
  {"id":"acc_121","exam":"ACCUPLACER","section":"Arithmetic","question":"What is 125% of 80?","options":[{"label":"A","text":"100"},{"label":"B","text":"90"},{"label":"C","text":"85"},{"label":"D","text":"105"}],"correctAnswer":"A","explanation":"125% × 80 = 1.25 × 80 = 100.","skill":"Percentages","difficulty":"medium"},
  {"id":"acc_122","exam":"ACCUPLACER","section":"Reading","question":"The purpose of a conclusion in a research paper is to:","options":[{"label":"A","text":"Summarize findings and suggest implications"},{"label":"B","text":"Present new data"},{"label":"C","text":"List all references"},{"label":"D","text":"Introduce the hypothesis"}],"correctAnswer":"A","explanation":"A conclusion summarizes key findings, discusses implications, and may suggest future research.","skill":"Research Writing","difficulty":"easy"},
  {"id":"acc_123","exam":"ACCUPLACER","section":"Writing","question":"Which shows correct apostrophe use?","options":[{"label":"A","text":"The dog's bone was buried in the yard."},{"label":"B","text":"The dogs' bone was buried in the yard. (one dog)"},{"label":"C","text":"The dog's' bone was buried in the yard."},{"label":"D","text":"The dogs bone was buried in the yard."}],"correctAnswer":"A","explanation":"For a singular possessive, add 's: dog's.","skill":"Apostrophes","difficulty":"easy"},
  {"id":"acc_124","exam":"ACCUPLACER","section":"Quantitative Reasoning","question":"A number is decreased by 20% and becomes 48. What was the original?","options":[{"label":"A","text":"60"},{"label":"B","text":"58"},{"label":"C","text":"40"},{"label":"D","text":"56"}],"correctAnswer":"A","explanation":"0.80x = 48 → x = 60.","skill":"Percent Applications","difficulty":"medium"},
  {"id":"acc_125","exam":"ACCUPLACER","section":"Advanced Algebra","question":"Simplify: (x³)²","options":[{"label":"A","text":"x⁶"},{"label":"B","text":"x⁵"},{"label":"C","text":"x⁹"},{"label":"D","text":"2x³"}],"correctAnswer":"A","explanation":"Power rule: (x³)² = x^(3×2) = x⁶.","skill":"Exponent Rules","difficulty":"easy"},
  {"id":"acc_126","exam":"ACCUPLACER","section":"Arithmetic","question":"What is √81?","options":[{"label":"A","text":"9"},{"label":"B","text":"8"},{"label":"C","text":"7"},{"label":"D","text":"81"}],"correctAnswer":"A","explanation":"9 × 9 = 81, so √81 = 9.","skill":"Square Roots","difficulty":"easy"},
  {"id":"acc_127","exam":"ACCUPLACER","section":"Reading","question":"An analogy compares:","options":[{"label":"A","text":"Two things that share a similar relationship"},{"label":"B","text":"Two identical items"},{"label":"C","text":"A word with its antonym only"},{"label":"D","text":"Nothing"}],"correctAnswer":"A","explanation":"An analogy shows that two pairs share a similar relationship pattern.","skill":"Analogies","difficulty":"easy"},
  {"id":"acc_128","exam":"ACCUPLACER","section":"Writing","question":"Which correctly uses 'than' vs 'then'?","options":[{"label":"A","text":"She is taller than her sister."},{"label":"B","text":"She is taller then her sister."},{"label":"C","text":"She studied, than she took the test."},{"label":"D","text":"First study, than take the test."}],"correctAnswer":"A","explanation":"'Than' is for comparisons. 'Then' indicates time or sequence.","skill":"Commonly Confused Words","difficulty":"easy"},
  {"id":"acc_129","exam":"ACCUPLACER","section":"Quantitative Reasoning","question":"What is the median of: 12, 7, 3, 15, 9?","options":[{"label":"A","text":"9"},{"label":"B","text":"12"},{"label":"C","text":"7"},{"label":"D","text":"9.2"}],"correctAnswer":"A","explanation":"Ordered: 3, 7, 9, 12, 15. Middle value = 9.","skill":"Median","difficulty":"easy"},
  {"id":"acc_130","exam":"ACCUPLACER","section":"Advanced Algebra","question":"What is the slope of a line perpendicular to y = 2x + 3?","options":[{"label":"A","text":"-1/2"},{"label":"B","text":"2"},{"label":"C","text":"1/2"},{"label":"D","text":"-2"}],"correctAnswer":"A","explanation":"Perpendicular slopes are negative reciprocals. Slope of 2 → perpendicular slope = -1/2.","skill":"Perpendicular Lines","difficulty":"medium"},
  {"id":"acc_131","exam":"ACCUPLACER","section":"Arithmetic","question":"Add: 2.3 + 4.75","options":[{"label":"A","text":"7.05"},{"label":"B","text":"7.5"},{"label":"C","text":"6.05"},{"label":"D","text":"7.08"}],"correctAnswer":"A","explanation":"2.30 + 4.75 = 7.05.","skill":"Decimal Addition","difficulty":"easy"},
  {"id":"acc_132","exam":"ACCUPLACER","section":"Reading","question":"When an author uses words like 'consequently' and 'as a result,' the text structure is:","options":[{"label":"A","text":"Cause and effect"},{"label":"B","text":"Compare and contrast"},{"label":"C","text":"Chronological"},{"label":"D","text":"Description"}],"correctAnswer":"A","explanation":"Signal words like 'consequently' and 'as a result' indicate cause and effect relationships.","skill":"Text Structure","difficulty":"easy"},
  {"id":"acc_133","exam":"ACCUPLACER","section":"Writing","question":"Identify the correctly punctuated title:","options":[{"label":"A","text":"\"The Tell-Tale Heart\" by Edgar Allan Poe"},{"label":"B","text":"The Tell-Tale Heart by Edgar Allan Poe"},{"label":"C","text":"The Tell-Tale Heart by Edgar Allan Poe"},{"label":"D","text":"\"The\" Tell-Tale Heart by Edgar Allan Poe"}],"correctAnswer":"A","explanation":"Short story titles go in quotation marks. Book titles would be italicized.","skill":"Title Formatting","difficulty":"easy"},
  {"id":"acc_134","exam":"ACCUPLACER","section":"Quantitative Reasoning","question":"Convert 2.5 kilometers to meters.","options":[{"label":"A","text":"2,500"},{"label":"B","text":"250"},{"label":"C","text":"25,000"},{"label":"D","text":"25"}],"correctAnswer":"A","explanation":"1 km = 1,000 m. 2.5 × 1,000 = 2,500 m.","skill":"Metric Conversion","difficulty":"easy"},
  {"id":"acc_135","exam":"ACCUPLACER","section":"Advanced Algebra","question":"Solve: x² + x - 12 = 0 using the quadratic formula or factoring.","options":[{"label":"A","text":"x = 3 or x = -4"},{"label":"B","text":"x = 4 or x = -3"},{"label":"C","text":"x = 6 or x = -2"},{"label":"D","text":"x = 12 or x = -1"}],"correctAnswer":"A","explanation":"Factor: (x+4)(x-3) = 0 → x = -4 or x = 3.","skill":"Quadratic Equations","difficulty":"medium"},
  {"id":"acc_136","exam":"ACCUPLACER","section":"Arithmetic","question":"What is 40% of 250?","options":[{"label":"A","text":"100"},{"label":"B","text":"90"},{"label":"C","text":"110"},{"label":"D","text":"150"}],"correctAnswer":"A","explanation":"40% × 250 = 0.40 × 250 = 100.","skill":"Percentages","difficulty":"easy"},
  {"id":"acc_137","exam":"ACCUPLACER","section":"Reading","question":"Which sentence is an opinion?","options":[{"label":"A","text":"Chocolate ice cream is the best flavor."},{"label":"B","text":"Water boils at 100°C at sea level."},{"label":"C","text":"The Earth orbits the Sun."},{"label":"D","text":"There are 50 states in the United States."}],"correctAnswer":"A","explanation":"'Best' makes this subjective — it's a personal preference, not a verifiable fact.","skill":"Fact vs Opinion","difficulty":"easy"},
  {"id":"acc_138","exam":"ACCUPLACER","section":"Writing","question":"A thesis statement should appear in which part of an essay?","options":[{"label":"A","text":"Introduction"},{"label":"B","text":"Conclusion"},{"label":"C","text":"Body paragraph 2"},{"label":"D","text":"Title"}],"correctAnswer":"A","explanation":"The thesis typically appears at the end of the introduction, presenting the essay's central argument.","skill":"Essay Structure","difficulty":"easy"},
  {"id":"acc_139","exam":"ACCUPLACER","section":"Quantitative Reasoning","question":"What is the simple interest on $1,000 at 5% for 3 years?","options":[{"label":"A","text":"$150"},{"label":"B","text":"$50"},{"label":"C","text":"$500"},{"label":"D","text":"$1,150"}],"correctAnswer":"A","explanation":"I = PRT = 1000 × 0.05 × 3 = $150.","skill":"Simple Interest","difficulty":"medium"},
  {"id":"acc_140","exam":"ACCUPLACER","section":"Advanced Algebra","question":"What is the midpoint of (2, 8) and (6, 4)?","options":[{"label":"A","text":"(4, 6)"},{"label":"B","text":"(8, 12)"},{"label":"C","text":"(3, 5)"},{"label":"D","text":"(4, 4)"}],"correctAnswer":"A","explanation":"Midpoint = ((2+6)/2, (8+4)/2) = (4, 6).","skill":"Midpoint Formula","difficulty":"easy"},
  {"id":"acc_141","exam":"ACCUPLACER","section":"Arithmetic","question":"Simplify: 24/32","options":[{"label":"A","text":"3/4"},{"label":"B","text":"12/16"},{"label":"C","text":"6/8"},{"label":"D","text":"2/3"}],"correctAnswer":"A","explanation":"GCF = 8. 24÷8=3, 32÷8=4.","skill":"Simplifying Fractions","difficulty":"easy"},
  {"id":"acc_142","exam":"ACCUPLACER","section":"Reading","question":"The word 'mitigate' most likely means:","options":[{"label":"A","text":"To make less severe"},{"label":"B","text":"To make worse"},{"label":"C","text":"To eliminate completely"},{"label":"D","text":"To ignore"}],"correctAnswer":"A","explanation":"'Mitigate' means to make less severe, painful, or harsh.","skill":"Vocabulary","difficulty":"medium"},
  {"id":"acc_143","exam":"ACCUPLACER","section":"Writing","question":"Which demonstrates correct use of a dash?","options":[{"label":"A","text":"The results—surprising as they were—changed everything."},{"label":"B","text":"The results surprising—as they were changed everything."},{"label":"C","text":"The—results surprising as they—were changed everything."},{"label":"D","text":"The results surprising as they were—changed—everything."}],"correctAnswer":"A","explanation":"Dashes set off parenthetical information that interrupts the sentence.","skill":"Dashes","difficulty":"medium"},
  {"id":"acc_144","exam":"ACCUPLACER","section":"Quantitative Reasoning","question":"If a scale model is 1:50 and the model building is 6 inches tall, how tall is the real building?","options":[{"label":"A","text":"300 inches (25 feet)"},{"label":"B","text":"50 inches"},{"label":"C","text":"600 inches"},{"label":"D","text":"56 inches"}],"correctAnswer":"A","explanation":"6 × 50 = 300 inches = 25 feet.","skill":"Scale","difficulty":"medium"},
  {"id":"acc_145","exam":"ACCUPLACER","section":"Advanced Algebra","question":"Solve: 2ˣ = 1/8","options":[{"label":"A","text":"x = -3"},{"label":"B","text":"x = 3"},{"label":"C","text":"x = -8"},{"label":"D","text":"x = 1/3"}],"correctAnswer":"A","explanation":"1/8 = 2⁻³, so x = -3.","skill":"Negative Exponents","difficulty":"medium"},
  {"id":"acc_146","exam":"ACCUPLACER","section":"Arithmetic","question":"Which is larger: 2/3 or 5/8?","options":[{"label":"A","text":"2/3"},{"label":"B","text":"5/8"},{"label":"C","text":"They are equal"},{"label":"D","text":"Cannot be determined"}],"correctAnswer":"A","explanation":"2/3 ≈ 0.667, 5/8 = 0.625. 2/3 > 5/8.","skill":"Comparing Fractions","difficulty":"easy"},
  {"id":"acc_147","exam":"ACCUPLACER","section":"Reading","question":"A rhetorical question is used to:","options":[{"label":"A","text":"Make a point rather than seek an answer"},{"label":"B","text":"Get factual information"},{"label":"C","text":"End a paragraph"},{"label":"D","text":"Introduce a character"}],"correctAnswer":"A","explanation":"Rhetorical questions emphasize a point — the answer is implied, not expected.","skill":"Rhetoric","difficulty":"easy"},
  {"id":"acc_148","exam":"ACCUPLACER","section":"Writing","question":"Choose the correct word: 'She was _____ to the idea of change.'","options":[{"label":"A","text":"averse"},{"label":"B","text":"adverse"},{"label":"C","text":"adverce"},{"label":"D","text":"avertse"}],"correctAnswer":"A","explanation":"'Averse' means having a strong dislike or opposition. 'Adverse' means harmful or unfavorable.","skill":"Commonly Confused Words","difficulty":"medium"},
  {"id":"acc_149","exam":"ACCUPLACER","section":"Quantitative Reasoning","question":"What is the mode of: 4, 7, 7, 2, 9, 7, 3?","options":[{"label":"A","text":"7"},{"label":"B","text":"4"},{"label":"C","text":"5.57"},{"label":"D","text":"2"}],"correctAnswer":"A","explanation":"Mode is the most frequent value. 7 appears three times.","skill":"Mode","difficulty":"easy"},
  {"id":"acc_150","exam":"ACCUPLACER","section":"Advanced Algebra","question":"What is the distance between (1, 2) and (4, 6)?","options":[{"label":"A","text":"5"},{"label":"B","text":"7"},{"label":"C","text":"25"},{"label":"D","text":"3"}],"correctAnswer":"A","explanation":"d = √((4-1)²+(6-2)²) = √(9+16) = √25 = 5.","skill":"Distance Formula","difficulty":"medium"},
  {"id":"acc_151","exam":"ACCUPLACER","section":"Arithmetic","question":"What is 7/10 as a percent?","options":[{"label":"A","text":"70%"},{"label":"B","text":"7%"},{"label":"C","text":"0.7%"},{"label":"D","text":"17%"}],"correctAnswer":"A","explanation":"7/10 = 0.70 = 70%.","skill":"Percent Conversion","difficulty":"easy"},
  {"id":"acc_152","exam":"ACCUPLACER","section":"Reading","question":"The author's viewpoint in a text can be identified by examining:","options":[{"label":"A","text":"Word choice, tone, and arguments presented"},{"label":"B","text":"The page numbers"},{"label":"C","text":"The font style"},{"label":"D","text":"The text length only"}],"correctAnswer":"A","explanation":"An author's viewpoint is revealed through their language choices, tone, and the arguments they make.","skill":"Author's Viewpoint","difficulty":"easy"},
  {"id":"acc_153","exam":"ACCUPLACER","section":"Writing","question":"Which sentence has no errors?","options":[{"label":"A","text":"Neither the students nor the teacher was prepared for the fire drill."},{"label":"B","text":"Neither the students nor the teacher were prepared for the fire drill."},{"label":"C","text":"Neither the students or the teacher was prepared for the fire drill."},{"label":"D","text":"Neither the students nor the teacher have been prepared for the fire drill."}],"correctAnswer":"A","explanation":"With 'neither...nor,' the verb agrees with the nearer subject ('teacher' = singular → 'was').","skill":"Subject-Verb Agreement","difficulty":"medium"},
  {"id":"acc_154","exam":"ACCUPLACER","section":"Quantitative Reasoning","question":"A 15% tip on a $42 meal is:","options":[{"label":"A","text":"$6.30"},{"label":"B","text":"$6.00"},{"label":"C","text":"$7.50"},{"label":"D","text":"$4.20"}],"correctAnswer":"A","explanation":"15% × $42 = 0.15 × 42 = $6.30.","skill":"Tip Calculations","difficulty":"easy"},
  {"id":"acc_155","exam":"ACCUPLACER","section":"Advanced Algebra","question":"Solve for x: log(x) = 2","options":[{"label":"A","text":"100"},{"label":"B","text":"10"},{"label":"C","text":"20"},{"label":"D","text":"1000"}],"correctAnswer":"A","explanation":"log base 10: 10² = 100, so x = 100.","skill":"Logarithms","difficulty":"medium"},
  {"id":"acc_156","exam":"ACCUPLACER","section":"Arithmetic","question":"Calculate: -12 ÷ (-3)","options":[{"label":"A","text":"4"},{"label":"B","text":"-4"},{"label":"C","text":"9"},{"label":"D","text":"-9"}],"correctAnswer":"A","explanation":"Negative ÷ negative = positive. 12 ÷ 3 = 4.","skill":"Integer Division","difficulty":"easy"},
  {"id":"acc_157","exam":"ACCUPLACER","section":"Reading","question":"A thesis statement should be:","options":[{"label":"A","text":"Specific and arguable"},{"label":"B","text":"Vague and broad"},{"label":"C","text":"A fact everyone agrees on"},{"label":"D","text":"A question"}],"correctAnswer":"A","explanation":"An effective thesis takes a clear, specific, debatable position.","skill":"Thesis Identification","difficulty":"easy"},
  {"id":"acc_158","exam":"ACCUPLACER","section":"Writing","question":"Which correctly lists items in a series?","options":[{"label":"A","text":"We need eggs, flour, sugar, and butter."},{"label":"B","text":"We need eggs flour sugar and butter."},{"label":"C","text":"We need, eggs flour, sugar and butter."},{"label":"D","text":"We need eggs, flour sugar, and, butter."}],"correctAnswer":"A","explanation":"Items in a series are separated by commas, with 'and' before the last item.","skill":"Serial Commas","difficulty":"easy"},
  {"id":"acc_159","exam":"ACCUPLACER","section":"Quantitative Reasoning","question":"What is 3/4 of an hour in minutes?","options":[{"label":"A","text":"45 minutes"},{"label":"B","text":"30 minutes"},{"label":"C","text":"40 minutes"},{"label":"D","text":"50 minutes"}],"correctAnswer":"A","explanation":"3/4 × 60 = 45 minutes.","skill":"Time Calculations","difficulty":"easy"},
  {"id":"acc_160","exam":"ACCUPLACER","section":"Advanced Algebra","question":"What is the equation of a line through (0, 0) with slope 5?","options":[{"label":"A","text":"y = 5x"},{"label":"B","text":"y = x + 5"},{"label":"C","text":"y = 5x + 5"},{"label":"D","text":"x = 5y"}],"correctAnswer":"A","explanation":"Through origin (b=0), slope 5: y = 5x.","skill":"Linear Equations","difficulty":"easy"},
  {"id":"acc_161","exam":"ACCUPLACER","section":"Arithmetic","question":"Round 2,467 to the nearest hundred.","options":[{"label":"A","text":"2,500"},{"label":"B","text":"2,400"},{"label":"C","text":"2,470"},{"label":"D","text":"2,000"}],"correctAnswer":"A","explanation":"The tens digit is 6 (≥5), so round up: 2,500.","skill":"Rounding","difficulty":"easy"},
  {"id":"acc_162","exam":"ACCUPLACER","section":"Reading","question":"An author's diction refers to:","options":[{"label":"A","text":"Their choice of words"},{"label":"B","text":"How fast they write"},{"label":"C","text":"The length of paragraphs"},{"label":"D","text":"The number of characters"}],"correctAnswer":"A","explanation":"Diction is the author's choice of words, which affects tone and meaning.","skill":"Literary Analysis","difficulty":"easy"},
  {"id":"acc_163","exam":"ACCUPLACER","section":"Writing","question":"Which revision best improves: 'There are many reasons why exercise is good for you.'","options":[{"label":"A","text":"Exercise improves cardiovascular health, mental clarity, and immune function."},{"label":"B","text":"Exercise is good because it's good for your health."},{"label":"C","text":"There are lots of reasons."},{"label":"D","text":"No change needed."}],"correctAnswer":"A","explanation":"Being specific with concrete benefits is stronger than vague generalities.","skill":"Specificity","difficulty":"easy"},
  {"id":"acc_164","exam":"ACCUPLACER","section":"Quantitative Reasoning","question":"If a coat costs $80 and sales tax is 6.5%, what is the total?","options":[{"label":"A","text":"$85.20"},{"label":"B","text":"$86.50"},{"label":"C","text":"$85.00"},{"label":"D","text":"$84.50"}],"correctAnswer":"A","explanation":"Tax = 6.5% × $80 = $5.20. Total = $85.20.","skill":"Tax Calculations","difficulty":"easy"},
  {"id":"acc_165","exam":"ACCUPLACER","section":"Advanced Algebra","question":"Simplify: (x²-4)/(x-2)","options":[{"label":"A","text":"x + 2"},{"label":"B","text":"x - 2"},{"label":"C","text":"x² - 2"},{"label":"D","text":"2x"}],"correctAnswer":"A","explanation":"Factor: (x+2)(x-2)/(x-2) = x+2 (where x ≠ 2).","skill":"Rational Expressions","difficulty":"medium"},
  {"id":"acc_166","exam":"ACCUPLACER","section":"Arithmetic","question":"What is 2³?","options":[{"label":"A","text":"8"},{"label":"B","text":"6"},{"label":"C","text":"9"},{"label":"D","text":"16"}],"correctAnswer":"A","explanation":"2³ = 2 × 2 × 2 = 8.","skill":"Exponents","difficulty":"easy"},
  {"id":"acc_167","exam":"ACCUPLACER","section":"Reading","question":"A persuasive essay most effectively uses:","options":[{"label":"A","text":"A combination of ethos, logos, and pathos"},{"label":"B","text":"Only personal stories"},{"label":"C","text":"Only statistics"},{"label":"D","text":"Only emotional appeals"}],"correctAnswer":"A","explanation":"The strongest persuasion combines credibility (ethos), logic (logos), and emotional appeal (pathos).","skill":"Persuasive Writing","difficulty":"medium"},
  {"id":"acc_168","exam":"ACCUPLACER","section":"Writing","question":"Which is a complex sentence?","options":[{"label":"A","text":"Although she was tired, she finished the project."},{"label":"B","text":"She was tired. She finished the project."},{"label":"C","text":"She was tired and finished the project."},{"label":"D","text":"She finished the project."}],"correctAnswer":"A","explanation":"A complex sentence has one independent and at least one dependent clause ('Although she was tired').","skill":"Sentence Types","difficulty":"easy"},
  {"id":"acc_169","exam":"ACCUPLACER","section":"Quantitative Reasoning","question":"A carpet costs $12 per square yard. A room is 4 yards by 5 yards. What is the cost?","options":[{"label":"A","text":"$240"},{"label":"B","text":"$108"},{"label":"C","text":"$120"},{"label":"D","text":"$60"}],"correctAnswer":"A","explanation":"Area = 4 × 5 = 20 sq yd. Cost = 20 × $12 = $240.","skill":"Area Cost","difficulty":"easy"},
  {"id":"acc_170","exam":"ACCUPLACER","section":"Advanced Algebra","question":"If f(x) = x + 3 and g(x) = 2x, what is f(g(2))?","options":[{"label":"A","text":"7"},{"label":"B","text":"10"},{"label":"C","text":"8"},{"label":"D","text":"5"}],"correctAnswer":"A","explanation":"g(2) = 4. f(4) = 4 + 3 = 7.","skill":"Function Composition","difficulty":"medium"},
  {"id":"acc_171","exam":"ACCUPLACER","section":"Arithmetic","question":"What is 3 + 2 × 4?","options":[{"label":"A","text":"11"},{"label":"B","text":"20"},{"label":"C","text":"14"},{"label":"D","text":"9"}],"correctAnswer":"A","explanation":"Order of operations: multiply first. 2 × 4 = 8, then 3 + 8 = 11.","skill":"Order of Operations","difficulty":"easy"},
  {"id":"acc_172","exam":"ACCUPLACER","section":"Reading","question":"A symbol in literature is:","options":[{"label":"A","text":"An object that represents a larger concept or idea"},{"label":"B","text":"A punctuation mark"},{"label":"C","text":"A character's name"},{"label":"D","text":"The setting of a story"}],"correctAnswer":"A","explanation":"A symbol is something concrete that represents something abstract (e.g., a dove symbolizes peace).","skill":"Symbolism","difficulty":"easy"},
  {"id":"acc_173","exam":"ACCUPLACER","section":"Writing","question":"Which revision removes the double negative: 'She can't hardly wait.'","options":[{"label":"A","text":"She can hardly wait."},{"label":"B","text":"She can't not wait."},{"label":"C","text":"She can't wait hardly."},{"label":"D","text":"No change needed."}],"correctAnswer":"A","explanation":"'Can't' and 'hardly' are both negatives. Remove one: 'She can hardly wait.'","skill":"Double Negatives","difficulty":"easy"},
  {"id":"acc_174","exam":"ACCUPLACER","section":"Quantitative Reasoning","question":"How many seconds are in 5 minutes?","options":[{"label":"A","text":"300"},{"label":"B","text":"500"},{"label":"C","text":"250"},{"label":"D","text":"60"}],"correctAnswer":"A","explanation":"5 × 60 = 300 seconds.","skill":"Time Conversion","difficulty":"easy"},
  {"id":"acc_175","exam":"ACCUPLACER","section":"Advanced Algebra","question":"What is the sum of interior angles of a pentagon?","options":[{"label":"A","text":"540°"},{"label":"B","text":"360°"},{"label":"C","text":"720°"},{"label":"D","text":"180°"}],"correctAnswer":"A","explanation":"(n-2) × 180° = (5-2) × 180° = 540°.","skill":"Polygon Angles","difficulty":"medium"},
  {"id":"acc_176","exam":"ACCUPLACER","section":"Arithmetic","question":"What is 9/10 - 3/10?","options":[{"label":"A","text":"3/5"},{"label":"B","text":"6/10"},{"label":"C","text":"12/10"},{"label":"D","text":"1/5"}],"correctAnswer":"A","explanation":"9/10 - 3/10 = 6/10 = 3/5.","skill":"Fraction Subtraction","difficulty":"easy"},
  {"id":"acc_177","exam":"ACCUPLACER","section":"Reading","question":"Paraphrasing requires:","options":[{"label":"A","text":"Restating the author's ideas in your own words"},{"label":"B","text":"Copying the text exactly"},{"label":"C","text":"Ignoring the original text"},{"label":"D","text":"Only changing one word"}],"correctAnswer":"A","explanation":"Paraphrasing means expressing someone else's ideas in your own words while maintaining the original meaning.","skill":"Paraphrasing","difficulty":"easy"},
  {"id":"acc_178","exam":"ACCUPLACER","section":"Writing","question":"Which revision fixes the misplaced modifier: 'She almost drove her car for 300 miles.'","options":[{"label":"A","text":"She drove her car for almost 300 miles."},{"label":"B","text":"Almost she drove her car for 300 miles."},{"label":"C","text":"She drove almost her car for 300 miles."},{"label":"D","text":"No change needed."}],"correctAnswer":"A","explanation":"'Almost' should modify '300 miles,' not 'drove.'","skill":"Misplaced Modifiers","difficulty":"medium"},
  {"id":"acc_179","exam":"ACCUPLACER","section":"Quantitative Reasoning","question":"What is the range of: 15, 22, 8, 30, 12?","options":[{"label":"A","text":"22"},{"label":"B","text":"15"},{"label":"C","text":"30"},{"label":"D","text":"17.4"}],"correctAnswer":"A","explanation":"Range = 30 - 8 = 22.","skill":"Range","difficulty":"easy"},
  {"id":"acc_180","exam":"ACCUPLACER","section":"Advanced Algebra","question":"Solve: √(x + 9) = 5","options":[{"label":"A","text":"16"},{"label":"B","text":"25"},{"label":"C","text":"4"},{"label":"D","text":"-4"}],"correctAnswer":"A","explanation":"Square both sides: x + 9 = 25 → x = 16.","skill":"Radical Equations","difficulty":"medium"},
  {"id":"acc_181","exam":"ACCUPLACER","section":"Arithmetic","question":"A recipe calls for 2 1/4 cups of flour. How many cups is that as an improper fraction?","options":[{"label":"A","text":"9/4"},{"label":"B","text":"8/4"},{"label":"C","text":"10/4"},{"label":"D","text":"7/4"}],"correctAnswer":"A","explanation":"2 × 4 + 1 = 9 → 9/4.","skill":"Mixed Numbers","difficulty":"easy"},
  {"id":"acc_182","exam":"ACCUPLACER","section":"Reading","question":"Ethos as a rhetorical strategy appeals to:","options":[{"label":"A","text":"The author's credibility and trustworthiness"},{"label":"B","text":"Emotions"},{"label":"C","text":"Logic and facts"},{"label":"D","text":"Humor"}],"correctAnswer":"A","explanation":"Ethos builds credibility by establishing the author's expertise, character, or trustworthiness.","skill":"Rhetoric","difficulty":"medium"},
  {"id":"acc_183","exam":"ACCUPLACER","section":"Writing","question":"Which is grammatically correct?","options":[{"label":"A","text":"The data suggest a new trend."},{"label":"B","text":"The data suggests a new trend."},{"label":"C","text":"The datas suggest a new trend."},{"label":"D","text":"The data suggesting a new trend."}],"correctAnswer":"A","explanation":"'Data' is technically plural (datum is singular), so 'suggest' is correct.","skill":"Grammar","difficulty":"medium"},
  {"id":"acc_184","exam":"ACCUPLACER","section":"Quantitative Reasoning","question":"If 3 workers can finish a job in 8 hours, how long would 6 workers take?","options":[{"label":"A","text":"4 hours"},{"label":"B","text":"16 hours"},{"label":"C","text":"2 hours"},{"label":"D","text":"12 hours"}],"correctAnswer":"A","explanation":"Double the workers = half the time. 8/2 = 4 hours (inverse proportion).","skill":"Work Rate","difficulty":"medium"},
  {"id":"acc_185","exam":"ACCUPLACER","section":"Advanced Algebra","question":"What type of function is f(x) = 3ˣ?","options":[{"label":"A","text":"Exponential"},{"label":"B","text":"Linear"},{"label":"C","text":"Quadratic"},{"label":"D","text":"Logarithmic"}],"correctAnswer":"A","explanation":"f(x) = 3ˣ has the variable in the exponent, making it exponential.","skill":"Function Types","difficulty":"easy"},
  {"id":"acc_186","exam":"ACCUPLACER","section":"Arithmetic","question":"What is the area of a square with side length 11?","options":[{"label":"A","text":"121"},{"label":"B","text":"44"},{"label":"C","text":"22"},{"label":"D","text":"110"}],"correctAnswer":"A","explanation":"Area = s² = 11² = 121.","skill":"Area","difficulty":"easy"},
  {"id":"acc_187","exam":"ACCUPLACER","section":"Reading","question":"The phrase 'the tip of the iceberg' means:","options":[{"label":"A","text":"A small visible part of a much larger issue"},{"label":"B","text":"Something very cold"},{"label":"C","text":"The highest point"},{"label":"D","text":"An exact measurement"}],"correctAnswer":"A","explanation":"This idiom means what's visible is only a small fraction of the whole.","skill":"Idioms","difficulty":"easy"},
  {"id":"acc_188","exam":"ACCUPLACER","section":"Writing","question":"Which shows correct MLA citation format for a book?","options":[{"label":"A","text":"Author last name, first name. Title. Publisher, Year."},{"label":"B","text":"Title by Author, Year"},{"label":"C","text":"Author (Year) Title"},{"label":"D","text":"Year. Author. Title."}],"correctAnswer":"A","explanation":"MLA format: Last name, First name. Title of Book. Publisher, Year.","skill":"Citations","difficulty":"medium"},
  {"id":"acc_189","exam":"ACCUPLACER","section":"Quantitative Reasoning","question":"A pie is divided into 8 equal slices. If 3 are eaten, what fraction remains?","options":[{"label":"A","text":"5/8"},{"label":"B","text":"3/8"},{"label":"C","text":"5/3"},{"label":"D","text":"3/5"}],"correctAnswer":"A","explanation":"8 - 3 = 5 slices remaining. 5/8 of the pie.","skill":"Fractions","difficulty":"easy"},
  {"id":"acc_190","exam":"ACCUPLACER","section":"Advanced Algebra","question":"What is the GCF of 12x³ and 18x²?","options":[{"label":"A","text":"6x²"},{"label":"B","text":"3x"},{"label":"C","text":"12x²"},{"label":"D","text":"36x³"}],"correctAnswer":"A","explanation":"GCF of 12,18 = 6. GCF of x³,x² = x². So 6x².","skill":"GCF with Variables","difficulty":"medium"},
  {"id":"acc_191","exam":"ACCUPLACER","section":"Arithmetic","question":"If you buy 3 items at $4.99 each, approximately how much will you spend?","options":[{"label":"A","text":"$15"},{"label":"B","text":"$12"},{"label":"C","text":"$20"},{"label":"D","text":"$10"}],"correctAnswer":"A","explanation":"Estimate: 3 × $5 = $15. Actual: $14.97.","skill":"Estimation","difficulty":"easy"},
  {"id":"acc_192","exam":"ACCUPLACER","section":"Reading","question":"A conclusion in a reading passage:","options":[{"label":"A","text":"Wraps up the argument and may call the reader to action"},{"label":"B","text":"Introduces new evidence"},{"label":"C","text":"States the thesis for the first time"},{"label":"D","text":"Only repeats the introduction"}],"correctAnswer":"A","explanation":"A conclusion synthesizes the argument, reinforces the thesis, and may include a call to action.","skill":"Text Structure","difficulty":"easy"},
  {"id":"acc_193","exam":"ACCUPLACER","section":"Writing","question":"Which sentence avoids the passive voice?","options":[{"label":"A","text":"The committee approved the budget."},{"label":"B","text":"The budget was approved by the committee."},{"label":"C","text":"The budget was approved."},{"label":"D","text":"Approval of the budget was given."}],"correctAnswer":"A","explanation":"'The committee approved' puts the subject doing the action first (active voice).","skill":"Active Voice","difficulty":"easy"},
  {"id":"acc_194","exam":"ACCUPLACER","section":"Quantitative Reasoning","question":"Convert 68°F to °C using C = 5/9(F - 32).","options":[{"label":"A","text":"20°C"},{"label":"B","text":"36°C"},{"label":"C","text":"15°C"},{"label":"D","text":"25°C"}],"correctAnswer":"A","explanation":"C = 5/9 × (68-32) = 5/9 × 36 = 20°C.","skill":"Temperature Conversion","difficulty":"medium"},
  {"id":"acc_195","exam":"ACCUPLACER","section":"Advanced Algebra","question":"If the sum of two consecutive integers is 37, what are they?","options":[{"label":"A","text":"18 and 19"},{"label":"B","text":"17 and 20"},{"label":"C","text":"16 and 21"},{"label":"D","text":"19 and 20"}],"correctAnswer":"A","explanation":"n + (n+1) = 37 → 2n = 36 → n = 18. Numbers: 18 and 19.","skill":"Word Problems","difficulty":"easy"},
  {"id":"acc_196","exam":"ACCUPLACER","section":"Arithmetic","question":"What is 50% of 50% of 100?","options":[{"label":"A","text":"25"},{"label":"B","text":"50"},{"label":"C","text":"75"},{"label":"D","text":"10"}],"correctAnswer":"A","explanation":"50% of 100 = 50. 50% of 50 = 25.","skill":"Compound Percentages","difficulty":"easy"},
  {"id":"acc_197","exam":"ACCUPLACER","section":"Reading","question":"An unreliable narrator:","options":[{"label":"A","text":"Cannot be fully trusted due to bias, limited knowledge, or deception"},{"label":"B","text":"Always tells the truth"},{"label":"C","text":"Is always the villain"},{"label":"D","text":"Is a third-person narrator"}],"correctAnswer":"A","explanation":"Unreliable narrators have compromised credibility, requiring readers to question the narrative.","skill":"Narrative Perspective","difficulty":"medium"},
  {"id":"acc_198","exam":"ACCUPLACER","section":"Writing","question":"Which sentence is punctuated correctly?","options":[{"label":"A","text":"\"Where are you going?\" she asked."},{"label":"B","text":"\"Where are you going\"? she asked."},{"label":"C","text":"\"Where are you going?\" She asked."},{"label":"D","text":"Where are you going? \"she asked.\""}],"correctAnswer":"A","explanation":"The question mark goes inside the quotation marks, and 'she asked' is lowercase (dialogue tag).","skill":"Dialogue Punctuation","difficulty":"medium"},
  {"id":"acc_199","exam":"ACCUPLACER","section":"Quantitative Reasoning","question":"A train travels at 60 mph. How far does it travel in 2.5 hours?","options":[{"label":"A","text":"150 miles"},{"label":"B","text":"120 miles"},{"label":"C","text":"180 miles"},{"label":"D","text":"125 miles"}],"correctAnswer":"A","explanation":"Distance = speed × time = 60 × 2.5 = 150 miles.","skill":"Distance","difficulty":"easy"},
  {"id":"acc_200","exam":"ACCUPLACER","section":"Advanced Algebra","question":"Solve: x³ = 27","options":[{"label":"A","text":"3"},{"label":"B","text":"9"},{"label":"C","text":"27"},{"label":"D","text":"√27"}],"correctAnswer":"A","explanation":"∛27 = 3 because 3³ = 27.","skill":"Cube Roots","difficulty":"easy"}
]